[{"type":"GPoint","name":"P1","parents":[],"x":217,"y":99,"builder":"PointBuilder","color":"rgb(255,255,255)"},{"type":"GPoint","name":"P2","parents":[],"x":518,"y":221,"builder":"PointBuilder","color":"rgb(255,255,255)"},{"type":"GPoint","name":"P3","parents":[],"x":506,"y":387,"builder":"PointBuilder","color":"rgb(255,255,255)"},{"type":"GPoint","name":"P4","parents":[],"x":95,"y":288,"builder":"PointBuilder","color":"rgb(255,255,255)"},{"type":"GSegment","name":"S1","parents":["P1","P2"],"builder":"SegmentBuilder","color":"rgb(0,255,0)"},{"type":"GSegment","name":"S2","parents":["P2","P3"],"builder":"SegmentBuilder","color":"rgb(0,255,0)"},{"type":"GSegment","name":"S3","parents":["P3","P4"],"builder":"SegmentBuilder","color":"rgb(0,255,0)"},{"type":"GSegment","name":"S4","parents":["P4","P1"],"builder":"SegmentBuilder","color":"rgb(0,255,0)"},{"type":"GPoint","name":"P5","parents":["P1","P2"],"x":367.5,"y":160,"builder":"MiddleBuilder","color":"rgb(255,255,255)"},{"type":"GPoint","name":"P6","parents":["P2","P3"],"x":512,"y":304,"builder":"MiddleBuilder","color":"rgb(255,255,255)"},{"type":"GPoint","name":"P7","parents":["P3","P4"],"x":300.5,"y":337.5,"builder":"MiddleBuilder","color":"rgb(255,255,255)"},{"type":"GPoint","name":"P8","parents":["P4","P1"],"x":156,"y":193.5,"builder":"MiddleBuilder","color":"rgb(255,255,255)"},{"type":"GSegment","name":"S5","parents":["P8","P5"],"builder":"SegmentBuilder","color":"rgb(255,255,255)"},{"type":"GSegment","name":"S6","parents":["P5","P6"],"builder":"SegmentBuilder","color":"rgb(255,255,255)"},{"type":"GSegment","name":"S7","parents":["P6","P7"],"builder":"SegmentBuilder","color":"rgb(255,255,255)"},{"type":"GSegment","name":"S8","parents":["P7","P8"],"builder":"SegmentBuilder","color":"rgb(255,255,255)"}]
